watermarker/__init__.py
watermarker/cli.py
watermarker/core.py
watermarker/utils.py
watermarker/gui/__init__.py
watermarker/gui/server.py
filewatermarker-0.1.1.dist-info/METADATA
filewatermarker-0.1.1.dist-info/WHEEL
filewatermarker-0.1.1.dist-info/entry_points.txt
filewatermarker-0.1.1.dist-info/top_level.txt
filewatermarker-0.1.1.dist-info/RECORD
