Metadata-Version: 2.4
Name: filewatermarker
Version: 0.1.1
Summary: A versatile tool for adding text or image watermarks to PDF documents and images
Author-email: Michael Jabbour <michael@example.com>
License-Expression: MIT
Classifier: Development Status :: 4 - Beta
Classifier: Intended Audience :: Developers
Classifier: Programming Language :: Python :: 3
Classifier: Programming Language :: Python :: 3.8
Classifier: Programming Language :: Python :: 3.9
Classifier: Programming Language :: Python :: 3.10
Classifier: Programming Language :: Python :: 3.11
Classifier: Programming Language :: Python :: 3.12
Requires-Python: >=3.8
Requires-Dist: reportlab>=3.6.12
Requires-Dist: pypdf>=3.15.1
Requires-Dist: Pillow>=9.4.0
Requires-Dist: tqdm>=4.64.1
Requires-Dist: pyyaml>=6.0
Provides-Extra: dev
Requires-Dist: pytest>=7.0; extra == "dev"
Requires-Dist: black>=23.0; extra == "dev"
Requires-Dist: isort>=5.0; extra == "dev"
Requires-Dist: mypy>=1.0; extra == "dev"
Requires-Dist: pytest-cov>=4.0; extra == "dev"
